<?xml version="1.0"?>
<FileSetup>
    <Input>input_maize/</Input>
    <Output>input_maize/output/</Output>
    <WeatherFilename>weather_maize.csv</WeatherFilename>
    <CO2Filename>MaunaLoaCO2.csv</CO2Filename>
    <ClockFilename>Clock.xml</ClockFilename>
    <CropRotationFilename>CropRotation.xml</CropRotationFilename>
    <FieldManagementFilename>FieldManagement.xml</FieldManagementFilename>
    <InitialSWCFilename>InitialSoilWaterContent.xml</InitialSWCFilename>
    <GroundwaterFilename>WaterTable.xml</GroundwaterFilename> 
    <SoilFilename>Soil.xml</SoilFilename>
<CropRotationCalendarFilename>CropRotationCalendar.csv</CropRotationCalendarFilename>
</FileSetup>